DLHelper/__init__.py
DLHelper/imports.py
DLHelper/image/Augmentor.py
DLHelper/image/CNNLearner.py
DLHelper/image/DataRaw.py
DLHelper/image/DataSplit.py
DLHelper/image/LearningRateFinder.py
DLHelper/image/Resizer.py
DLHelper/image/TrainCycle.py
DLHelper/image/__init__.py
DLHelper/image/discriminative_lr.py
DLHelper/image/triplet_loss.py
DLHelper/image/utils/RISutils.py
DLHelper/image/utils/__init__.py
DLHelper/image/utils/get_image_size.py
DLHelper/image/utils/tf_resizer.py
DLHelper/image/utils/utils.py
DLHelper-0.0.9.6.dist-info/LICENSE.txt
DLHelper-0.0.9.6.dist-info/METADATA
DLHelper-0.0.9.6.dist-info/WHEEL
DLHelper-0.0.9.6.dist-info/top_level.txt
DLHelper-0.0.9.6.dist-info/RECORD
