Metadata-Version: 2.1
Name: DLHelper
Version: 0.0.9.6
Summary: Tensorflow/keras based toolset to speed up DL model creation and training
Home-page: https://github.com/user/LukasNorbutas
Author: Lukas Norbutas
Author-email: lukas.norbutas@gmail.com
License: MIT
Download-URL: https://github.com/LukasNorbutas/DLHelper
Platform: UNKNOWN
Requires-Dist: numpy
Requires-Dist: pandas
Requires-Dist: matplotlib
Requires-Dist: seaborn
Requires-Dist: scikit-image
Requires-Dist: scikit-learn
Requires-Dist: scikit-optimize
